frizzle/__init__.py
frizzle/utils.py
frizzle-0.1.3.dist-info/licenses/LICENSE
frizzle-0.1.3.dist-info/METADATA
frizzle-0.1.3.dist-info/WHEEL
frizzle-0.1.3.dist-info/top_level.txt
frizzle-0.1.3.dist-info/RECORD
