Metadata-Version: 2.4
Name: frizzle
Version: 0.1.3
Summary: Combine spectra by forward modelling
Author-email: "Andrew R. Casey" <andrew.casey@monash.edu>, "David W. Hogg" <david.hogg@nyu.edu>
Maintainer-email: Andy Casey <andrew.casey@monash.edu>
License: LICENSE.md
Keywords: astronomy software
Requires-Python: >=3.9
License-File: LICENSE
Requires-Dist: numpy
Requires-Dist: finufft
Requires-Dist: pylops
Requires-Dist: scipy
Requires-Dist: scikit-learn
Requires-Dist: jax>=0.4.30
Requires-Dist: jaxlib>=0.4.30
Requires-Dist: nifty-solve>=0.1.2
Provides-Extra: dev
Requires-Dist: pytest; extra == "dev"
Requires-Dist: pytest-cov; extra == "dev"
Requires-Dist: pytest-sugar; extra == "dev"
Requires-Dist: pre-commit; extra == "dev"
Requires-Dist: black; extra == "dev"
Dynamic: license-file
